rangeutils/__init__.py
rangeutils/range_utils.py
rangeutils/version.py
rangeutils-0.1.3.dist-info/LICENSE
rangeutils-0.1.3.dist-info/WHEEL
rangeutils-0.1.3.dist-info/METADATA
rangeutils-0.1.3.dist-info/RECORD
