Metadata-Version: 2.1
Name: rangeutils
Version: 0.1.3
Summary: Utilities for manipulating and converting Python ranges and boolean lists
Home-page: https://github.com/Hom-Wang/rangeutils
License: MIT
Author: kris.wang
Author-email: wenhom.wang@gmail.com
Requires-Python: >=3.10,<4.0
Classifier: License :: OSI Approved :: MIT License
Classifier: Programming Language :: Python :: 3
Classifier: Programming Language :: Python :: 3.10
Requires-Dist: numpy (>=2.1.1,<3.0.0)
Project-URL: Repository, https://github.com/Hom-Wang/rangeutils
